{
  "cadence": {
    "grace_seconds": 5,
    "kind": "candle_close",
    "timeframe": "1h"
  },
  "margin_mode": "cross",
  "max_concurrent_position_tokens": 2.0,
  "max_firings": 24,
  "rules": [
    {
      "cooldown": "until_condition_resets",
      "do": {
        "kind": "open",
        "side": "buy",
        "size": {
          "tokens": 0.5
        }
      },
      "name": "entry-long-macd-adx",
      "only_if_position": "flat",
      "when": {
        "all": [
          {
            "compare": {
              "left": {
                "indicator": {
                  "key": "hist",
                  "kind": "macd",
                  "timeframe": "1h"
                }
              },
              "op": "gt",
              "right": {
                "constant": 0.0
              }
            }
          },
          {
            "compare": {
              "left": {
                "indicator": {
                  "kind": "adx",
                  "period": 14,
                  "timeframe": "1h"
                }
              },
              "op": "gt",
              "right": {
                "constant": 25.0
              }
            }
          }
        ]
      }
    },
    {
      "cooldown": "until_condition_resets",
      "do": {
        "fraction": 0.5,
        "kind": "reduce"
      },
      "name": "trim-long-macd-flip",
      "only_if_position": "long",
      "when": {
        "crosses": {
          "direction": "below",
          "left": {
            "indicator": {
              "key": "hist",
              "kind": "macd",
              "timeframe": "1h"
            }
          },
          "right": {
            "constant": 0.0
          }
        }
      }
    },
    {
      "cooldown": {
        "min_ticks": {
          "ticks": 4
        }
      },
      "do": {
        "kind": "close"
      },
      "name": "close-long-adx-fades",
      "only_if_position": "long",
      "when": {
        "compare": {
          "left": {
            "indicator": {
              "kind": "adx",
              "period": 14,
              "timeframe": "1h"
            }
          },
          "op": "lt",
          "right": {
            "constant": 15.0
          }
        }
      }
    }
  ],
  "symbol": "SOL"
}
